README.md
setup.cfg
setup.py
mensor/__init__.py
mensor/_version.py
mensor/constraints.py
mensor/context.py
mensor.egg-info/PKG-INFO
mensor.egg-info/SOURCES.txt
mensor.egg-info/dependency_links.txt
mensor.egg-info/requires.txt
mensor.egg-info/top_level.txt
mensor/backends/__init__.py
mensor/backends/pandas.py
mensor/backends/sql.py
mensor/library/__init__.py
mensor/library/ratio.py
mensor/measures/__init__.py
mensor/measures/provider.py
mensor/measures/registry.py
mensor/measures/stats.py
mensor/measures/strategy.py
mensor/measures/types.py
mensor/metrics/__init__.py
mensor/metrics/registry.py
mensor/metrics/types.py
mensor/utils/__init__.py
mensor/utils/registry.py