Metadata-Version: 2.1
Name: mensor
Version: 0.3.0
Summary: A dynamic graph-based metric computation engine.
Home-page: http://github.com/airbnb/mensor
Author: Matthew Wardrop
Author-email: mpwardrop@gmail.com
License: MIT
Project-URL: Documentation, http://mensor.readthedocs.io
Project-URL: Source, https://github.com/airbnb/mensor
Project-URL: Issue Tracker, https://github.com/airbnb/mensor/issues
Keywords: measures metrics aggregation experimentation statistics
Platform: UNKNOWN
Classifier: Development Status :: 3 - Alpha
Classifier: Environment :: Console
Classifier: Intended Audience :: Developers
Classifier: Intended Audience :: Information Technology
Classifier: Intended Audience :: Science/Research
Classifier: License :: OSI Approved :: MIT License
Classifier: Programming Language :: Python :: 3
Classifier: Programming Language :: Python :: 3.4
Classifier: Programming Language :: Python :: 3.5
Classifier: Programming Language :: Python :: 3.6
Requires-Python: ~=3.4
